pymycobot/Interface.py
pymycobot/__init__.py
pymycobot/bluet.py
pymycobot/close_loop.py
pymycobot/common.py
pymycobot/conveyor_api.py
pymycobot/dualcobotx.py
pymycobot/elephantrobot.py
pymycobot/end_control.py
pymycobot/error.py
pymycobot/exoskeleton.py
pymycobot/exoskeletonsocket.py
pymycobot/generate.py
pymycobot/genre.py
pymycobot/log.py
pymycobot/mecharm.py
pymycobot/mecharm270.py
pymycobot/mecharmsocket.py
pymycobot/mercury.py
pymycobot/mercury_api.py
pymycobot/mercury_arms_socket.py
pymycobot/mercury_ros_api.py
pymycobot/mercurychassis.py
pymycobot/mercurychassis_api.py
pymycobot/mercurysocket.py
pymycobot/myagv.py
pymycobot/myagvapi.py
pymycobot/myagvpro.py
pymycobot/myagvpro_bluetooth.py
pymycobot/myagvpro_socket.py
pymycobot/myarm.py
pymycobot/myarm_api.py
pymycobot/myarmc.py
pymycobot/myarmm.py
pymycobot/myarmm_control.py
pymycobot/myarmsocket.py
pymycobot/mybuddy.py
pymycobot/mybuddybluetooth.py
pymycobot/mybuddyemoticon.py
pymycobot/mybuddysocket.py
pymycobot/mycobot.py
pymycobot/mycobot280.py
pymycobot/mycobot280rdkx5.py
pymycobot/mycobot280socket.py
pymycobot/mycobot280x5pi.py
pymycobot/mycobot320.py
pymycobot/mycobot320socket.py
pymycobot/mycobotpro630.py
pymycobot/mycobotsocket.py
pymycobot/mypalletizer.py
pymycobot/mypalletizer260.py
pymycobot/mypalletizersocket.py
pymycobot/pro400.py
pymycobot/pro400client.py
pymycobot/pro450client.py
pymycobot/pro630.py
pymycobot/pro630client.py
pymycobot/pro630common.py
pymycobot/progripper.py
pymycobot/protocol_packet_handler.py
pymycobot/public.py
pymycobot/robot_info.py
pymycobot/sms.py
pymycobot/tool_coords.py
pymycobot/ultraArm.py
pymycobot/ultraArmP1.py
pymycobot/ultraArmP340.py
pymycobot/utils.py
tests/__init__.py
tests/conftest.py
tests/rasp_myArm_test_gui.py
tests/rasp_mycobot_test_gui.py
tests/rasp_mypall_test_gui.py
tests/special_angles.py
tests/test_api.py
tests/test_generator.py
tests/test_socket.py
tests/test_utils.py
pymycobot-4.0.3.dist-info/LICENSE
pymycobot-4.0.3.dist-info/METADATA
pymycobot-4.0.3.dist-info/WHEEL
pymycobot-4.0.3.dist-info/top_level.txt
pymycobot-4.0.3.dist-info/RECORD
