Metadata-Version: 2.1
Name: pymycobot
Version: 4.0.3
Summary: Python API for serial communication of MyCobot.
Home-page: https://github.com/elephantrobotics/pymycobot
Author: Elephantrobotics
Author-email: weiquan.xu@elephantrobotics.com
Classifier: Programming Language :: Python :: 3.5
Classifier: Programming Language :: Python :: 3.6
Classifier: Programming Language :: Python :: 3.7
Classifier: Programming Language :: Python :: 3.8
Classifier: Programming Language :: Python :: 3.9
Classifier: Programming Language :: Python :: 3.10
Classifier: License :: OSI Approved :: MIT License
Classifier: Operating System :: OS Independent
Requires-Python: >2.7, !=3.0.*, !=3.1.*, !=3.2.*, !=3.3.*, != 3.4.*
License-File: LICENSE
